Workbook

Sheet README
A1: TFS Dashboard 2.0 — Upload Workbook (aligned to Odoo extract 004)
A3: MONTHLY REFRESH — 3 steps:
A4: 1. Run extract 004 in Odoo. Delete old rows in RAW_004 (keep row 1), then paste the new export's rows
A5: (all 13 columns, without the header row) starting at cell A2. Column N fills in automatically.
A6: 2. Open UPLOAD. If the CHECKS block flags a mismatch, it usually means new staff/project/month
A7: combinations appeared: add the missing rows in ALLOCATIONS and/or MAPPING until all checks say OK.
A8: 3. Export the UPLOAD tab (File > Save As > CSV while on the UPLOAD tab) and upload it to the TFS Dashboard.
A10: TAB GUIDE:
A11: RAW_004 Paste target for the raw Odoo export. Columns must stay in Odoo's order:
A12: Created by | Date | Description | Employee | Last Updated by | Last Updated on |
A13: Parent Task | Project | Quantity | Sales Order Item | Task | Billable | Billable Type
A14: ALLOCATIONS One row per staff x project x month. Fill the yellow 'Allocated Hours' column with planned
... A26: and re-export rather than editing this workbook.

Sheet RAW_004
A1: Created by | B1: Date | C1: Description | D1: Employee | E1: Last Updated by | F1: Last Updated on | G1: Parent Task | H1: Project | I1: Quantity | J1: Sales Order Item | K1: Task | L1: Billable | M1: Billable Type | N1: Month (auto)
A2: Augustus Asamoah | B2: 46213 | C2: / | D2: Augustus Asamoah | E2: Augustus Asamoah | F2: 46210.376 | H2: P13PC00A00 - Private Sector Companies | I2: 0 | K2: Seedling Procurement and Supply | L2: FALSE | M2: Non-Billable | N2: =IF(B2="","",IF(ISNUMBER(B2),TEXT(B2,"YYYY-MM"),LEFT(B2,7)))
A3: Augustus Asamoah | B3: 46213 | C3: / | D3: Augustus Asamoah | E3: Augustus Asamoah | F3: 46210.376 | H3: P13QC00A00 - EFI Programme | I3: 0 | K3: Seedling Procurement and Supply | L3: FALSE | M3: Non-Billable | N3: =IF(B3="","",IF(ISNUMBER(B3),TEXT(B3,"YYYY-MM"),LEFT(B3,7)))
A4: Augustus Asamoah | B4: 46213 | C4: / | D4: Augustus Asamoah | E4: Augustus Asamoah | F4: 46210.376 | H4: P13NC00A00 - WALMART II | I4: 0 | K4: Check in call with Simon | L4: FALSE | M4: Non-Billable | N4: =IF(B4="","",IF(ISNUMBER(B4),TEXT(B4,"YYYY-MM"),LEFT(B4,7)))
A5: Augustus Asamoah | B5: 46213 | C5: / | D5: Augustus Asamoah | E5: Augustus Asamoah | F5: 46210.376 | H5: P13QC00A00 - EFI Programme | I5: 0 | K5: Review meeting and launch of tree planting in Takoradi | L5: FALSE | M5: Non-Billable | N5: =IF(B5="","",IF(ISNUMBER(B5),TEXT(B5,"YYYY-MM"),LEFT(B5,7)))
A6: Augustus Asamoah | B6: 46212 | C6: / | D6: Augustus Asamoah | E6: Augustus Asamoah | F6: 46210.376 | H6: P13QC00A00 - EFI Programme | I6: 0 | K6: Review meeting and launch of tree planting in Takoradi | L6: FALSE | M6: Non-Billable | N6: =IF(B6="","",IF(ISNUMBER(B6),TEXT(B6,"YYYY-MM"),LEFT(B6,7)))
A7: Augustus Asamoah | B7: 46211 | C7: / | D7: Augustus Asamoah | E7: Augustus Asamoah | F7: 46210.376 | H7: P13QC00A00 - EFI Programme | I7: 0 | K7: Review meeting and launch of tree planting in Takoradi | L7: FALSE | M7: Non-Billable | N7: =IF(B7="","",IF(ISNUMBER(B7),TEXT(B7,"YYYY-MM"),LEFT(B7,7)))
A8: Ekow Nyamekye Tawiah | B8: 46210 | C8: Proposal for BUA Bonsucro CHoC Standard | D8: Ekow Nyamekye Tawiah | E8: Ekow Nyamekye Tawiah | F8: 46210.653 | H8: Non-Billable Tasks | I8: 0 | K8: Business Development and Networking | L8: FALSE | M8: Non-Billable | N8: =IF(B8="","",IF(ISNUMBER(B8),TEXT(B8,"YYYY-MM"),LEFT(B8,7)))
A9: Ekow Nyamekye Tawiah | B9: 46210 | C9: Data review and reporting framework | D9: Ekow Nyamekye Tawiah | E9: Ekow Nyamekye Tawiah | F9: 46210.648 | H9: PCGH738 | I9: 1 | J9: PCGH738 - Analysis and Reporting (3) (Barnsley International Limited) | K9: Analysis and Reporting (3) | L9: TRUE | M9: Billed at a Fixed price | N9: =IF(B9="","",IF(ISNUMBER(B9),TEXT(B9,"YYYY-MM"),LEFT(B9,7)))
A10: Ekow Nyamekye Tawiah | B10: 46210 | C10: Annual Review with line Manager | D10: Ekow Nyamekye Tawiah | E10: Ekow Nyamekye Tawiah | F10: 46210.644 | H10: Non-Billable Tasks | I10: 0 | K10: Line Management | L10: FALSE | M10: Non-Billable | N10: =IF(B10="","",IF(ISNUMBER(B10),TEXT(B10,"YYYY-MM"),LEFT(B10,7)))
A11: Augustus Asamoah | B11: 46210 | C11: / | D11: Augustus Asamoah | E11: Augustus Asamoah | F11: 46210.376 | H11: P13QC00A00 - EFI Programme | I11: 0 | K11: Review meeting and launch of tree planting in Takoradi | L11: FALSE | M11: Non-Billable | N11: =IF(B11="","",IF(ISNUMBER(B11),TEXT(B11,"YYYY-MM"),LEFT(B11,7)))
A12: Augustus Asamoah | B12: 46210 | C12: / | D12: Augustus Asamoah | E12: Augustus Asamoah | F12: 46210.373 | H12: P13QC00A00 - EFI Programme | I12: 0 | K12: Follow up on field wrok and related activities | L12: FALSE | M12: Non-Billable | N12: =IF(B12="","",IF(ISNUMBER(B12),TEXT(B12,"YYYY-MM"),LEFT(B12,7)))
A13: Augustus Asamoah | B13: 46210 | C13: / | D13: Augustus Asamoah | E13: Augustus Asamoah | F13: 46210.376 | H13: P13PC00A00 - Private Sector Companies | I13: 0 | K13: coordination of MTS and related Activities | L13: FALSE | M13: Non-Billable | N13: =IF(B13="","",IF(ISNUMBER(B13),TEXT(B13,"YYYY-MM"),LEFT(B13,7)))
A14: Augustus Asamoah | B14: 46210 | C14: / | D14: Augustus Asamoah | E14: Augustus Asamoah | F14: 46210.376 | H14: P13NC00A00 - WALMART II | I14: 0 | K14: Check in call with Simon | L14: FALSE | M14: Non-Billable | N14: =IF(B14="","",IF(ISNUMBER(B14),TEXT(B14,"YYYY-MM"),LEFT(B14,7)))
A15: Augustus Asamoah | B15: 46210 | C15: / | D15: Augustus Asamoah | E15: Augustus Asamoah | F15: 46210.376 | H15: P13NC00A00 - WALMART II | I15: 0 | K15: RSC Procurements | L15: FALSE | M15: Non-Billable | N15: =IF(B15="","",IF(ISNUMBER(B15),TEXT(B15,"YYYY-MM"),LEFT(B15,7)))
A16: Augustus Asamoah | B16: 46210 | C16: / | D16: Augustus Asamoah | E16: Augustus Asamoah | F16: 46210.376 | H16: P13PC00A00 - Private Sector Companies | I16: 0 | K16: Support for A-A HMB | L16: FALSE | M16: Non-Billable | N16: =IF(B16="","",IF(ISNUMBER(B16),TEXT(B16,"YYYY-MM"),LEFT(B16,7)))
A17: Augustus Asamoah | B17: 46210 | C17: / | D17: Augustus Asamoah | E17: Augustus Asamoah | F17: 46210.366 | H17: P13PC00A00 - Private Sector Companies | I17: 0 | K17: Seedling Procurement and Supply | L17: FALSE | M17: Non-Billable | N17: =IF(B17="","",IF(ISNUMBER(B17),TEXT(B17,"YYYY-MM"),LEFT(B17,7)))
A18: Augustus Asamoah | B18: 46210 | C18: / | D18: Augustus Asamoah | E18: Augustus Asamoah | F18: 46210.365 | H18: P13QC00A00 - EFI Programme | I18: 0 | K18: Seedling Procurement and Supply | L18: FALSE | M18: Non-Billable | N18: =IF(B18="","",IF(ISNUMBER(B18),TEXT(B18,"YYYY-MM"),LEFT(B18,7)))
A19: Augustus Asamoah | B19: 46210 | C19: / | D19: Augustus Asamoah | E19: Augustus Asamoah | F19: 46210.364 | H19: P13NC00A00 - WALMART II | I19: 0 | K19: Seedling Procurement and Supply for MTS | L19: FALSE | M19: Non-Billable | N19: =IF(B19="","",IF(ISNUMBER(B19),TEXT(B19,"YYYY-MM"),LEFT(B19,7)))
A20: Augustus Asamoah | B20: 46210 | C20: / | D20: Augustus Asamoah | E20: Augustus Asamoah | F20: 46210.364 | H20: P13NC00A00 - WALMART II | I20: 0 | K20: Seedling Procurement and Supply for MTS | L20: FALSE | M20: Non-Billable | N20: =IF(B20="","",IF(ISNUMBER(B20),TEXT(B20,"YYYY-MM"),LEFT(B20,7)))
A21: Ekow Nyamekye Tawiah | B21: 46209 | C21: / | D21: Ekow Nyamekye Tawiah | E21: Ekow Nyamekye Tawiah | F21: 46210.653 | H21: Non-Billable Tasks | I21: 2.5 | K21: Business Development and Networking | L21: FALSE | M21: Non-Billable | N21: =IF(B21="","",IF(ISNUMBER(B21),TEXT(B21,"YYYY-MM"),LEFT(B21,7)))
... A27: Augustus Asamoah | B27: 46209 | C27: / | D27: Augustus Asamoah | E27: Augustus Asamoah | F27: 46210.376 | H27: P13NC00A00 - WALMART II | I27: 0 | K27: Seedling Procurement and Supply for MTS | L27: FALSE | M27: Non-Billable | N27: =IF(B27="","",IF(ISNUMBER(B27),TEXT(B27,"YYYY-MM"),LEFT(B27,7)))
A28: Ekow Nyamekye Tawiah | B28: 46209 | C28: Review and Rerun of Reunion Deforestation Risk Analysis. | D28: Ekow Nyamekye Tawiah | E28: Ekow Nyamekye Tawiah | F28: 46209.382 | H28: PCGH778 - General Support | I28: 0 | J28: PCGH778 - Support to Other Workstreams (3) (Proforest Limited(PCUK GBP)) | K28: (WS3: Deforestation) Deforestation Remote Risk Assessment | L28: TRUE | M28: Billed at a Fixed price | N28: =IF(B28="","",IF(ISNUMBER(B28),TEXT(B28,"YYYY-MM"),LEFT(B28,7)))
A29: Ekow Nyamekye Tawiah | B29: 46209 | C29: Republic Day | D29: Ekow Nyamekye Tawiah | E29: Ekow Nyamekye Tawiah | F29: 46209.38 | H29: Non-Billable Tasks | I29: 0 | K29: Public Holiday | L29: FALSE | M29: Non-Billable | N29: =IF(B29="","",IF(ISNUMBER(B29),TEXT(B29,"YYYY-MM"),LEFT(B29,7)))
A30: Abel Ansu | B30: 46206 | C30: Supply of seedlings from Gambia to Bitre and Biaso Kasapin | D30: Abel Ansu | E30: Abel Ansu | F30: 46210.372 | H30: P13PC00A00 - Private Sector Companies | I30: 8 | K30: Personnel Cost | L30: FALSE | M30: Non-Billable | N30: =IF(B30="","",IF(ISNUMBER(B30),TEXT(B30,"YYYY-MM"),LEFT(B30,7)))
A31: Ekow Nyamekye Tawiah | B31: 46206 | C31: / | D31: Ekow Nyamekye Tawiah | E31: Ekow Nyamekye Tawiah | F31: 46209.38 | H31: Non-Billable Tasks | I31: 4 | K31: Public Holiday | L31: FALSE | M31: Non-Billable | N31: =IF(B31="","",IF(ISNUMBER(B31),TEXT(B31,"YYYY-MM"),LEFT(B31,7)))
A32: Stephen Doso | B32: 46206 | C32: / | D32: Stephen Doso | E32: Stephen Doso | F32: 46209.346 | H32: Non-Billable Tasks | I32: 8 | K32: Public Holiday | L32: FALSE | M32: Non-Billable | N32: =IF(B32="","",IF(ISNUMBER(B32),TEXT(B32,"YYYY-MM"),LEFT(B32,7)))
A33: Louis Defo | B33: 46206 | C33: Go the Dja et Lobo division for some stakeholders engagaments | D33: Louis Defo | E33: Louis Defo | F33: 46209.315 | H33: PCGH787 | I33: 8 | J33: PCGH787 - Desk Study (3) (Proforest Limited(PCUK GBP)) | L33: TRUE | M33: Billed at a Fixed price | N33: =IF(B33="","",IF(ISNUMBER(B33),TEXT(B33,"YYYY-MM"),LEFT(B33,7)))
A34: Abel Ansu | B34: 46205 | C34: Monitoring of lining and pegging | D34: Abel Ansu | E34: Abel Ansu | F34: 46210.371 | H34: P13NC00A00 - WALMART II | I34: 8 | K34: Programme Personnel and Management | L34: FALSE | M34: Non-Billable | N34: =IF(B34="","",IF(ISNUMBER(B34),TEXT(B34,"YYYY-MM"),LEFT(B34,7)))
A35: Stephen Doso | B35: 46205 | C35: / | D35: Stephen Doso | E35: Stephen Doso | F35: 46209.542 | H35: PCGH775 - ESDD of Valency Operations for FMO | I35: 1 | J35: PCGH775 - Field Verification (2) (Valency International DMCC) | K35: Field verification and reporting in Nigeria (2) | L35: TRUE | M35: Billed at a Fixed price | N35: =IF(B35="","",IF(ISNUMBER(B35),TEXT(B35,"YYYY-MM"),LEFT(B35,7)))
A36: Stephen Doso | B36: 46205 | C36: / | D36: Stephen Doso | E36: Stephen Doso | F36: 46209.538 | H36: Non-Billable Tasks | I36: 1.5 | K36: Senior Management Activities | L36: FALSE | M36: Non-Billable | N36: =IF(B36="","",IF(ISNUMBER(B36),TEXT(B36,"YYYY-MM"),LEFT(B36,7)))
A37: Stephen Doso | B37: 46205 | C37: Dangote Sugar Call | D37: Stephen Doso | E37: Stephen Doso | F37: 46209.538 | H37: Non-Billable Tasks | I37: 0.5 | K37: Ad Hoc Time on Projects / Programmes | L37: FALSE | M37: Non-Billable | N37: =IF(B37="","",IF(ISNUMBER(B37),TEXT(B37,"YYYY-MM"),LEFT(B37,7)))
A38: Ekow Nyamekye Tawiah | B38: 46205 | C38: Deforestation Risk Analysis for Cameroon, Mauritius, Mozambique, Nigeria and Reunion (Run Analysis) | D38: Ekow Nyamekye Tawiah | E38: Ekow Nyamekye Tawiah | F38: 46209.387 | H38: PCGH778 - General Support | I38: 4 | J38: PCGH778 - Support to Other Workstreams (3) (Proforest Limited(PCUK GBP)) | K38: (WS3: Deforestation) Deforestation Remote Risk Assessment | L38: TRUE | M38: Billed at a Fixed price | N38: =IF(B38="","",IF(ISNUMBER(B38),TEXT(B38,"YYYY-MM"),LEFT(B38,7)))
A39: Ekow Nyamekye Tawiah | B39: 46205 | C39: / | D39: Ekow Nyamekye Tawiah | E39: Ekow Nyamekye Tawiah | F39: 46209.381 | H39: PCGH778 - General Support | I39: 0 | J39: PCGH778 - Support to Other Workstreams (3) (Proforest Limited(PCUK GBP)) | L39: TRUE | M39: Billed at a Fixed price | N39: =IF(B39="","",IF(ISNUMBER(B39),TEXT(B39,"YYYY-MM"),LEFT(B39,7)))
A40: Louis Defo | B40: 46205 | C40: participate to Cameroon cocoa week in order to do some stakeholdesr engagements | D40: Louis Defo | E40: Louis Defo | F40: 46209.314 | H40: PCGH787 | I40: 8 | J40: PCGH787 - Desk Study (3) (Proforest Limited(PCUK GBP)) | L40: TRUE | M40: Billed at a Fixed price | N40: =IF(B40="","",IF(ISNUMBER(B40),TEXT(B40,"YYYY-MM"),LEFT(B40,7)))
A41: Afua Serwah Akoto Prempeh | B41: 46205 | C41: Internal meeting to review feedback from TCI, agree on next steps, discuss meeting in Cameroon and provide input into brainstorming sessions. | D41: Afua Serwah Akoto Prempeh | E41: Afua Serwah Akoto Prempeh | F41: 46205.5 | H41: P23AC00C00 - FGMC | I41: 2 | L41: FALSE | M41: Non-Billable | N41: =IF(B41="","",IF(ISNUMBER(B41),TEXT(B41,"YYYY-MM"),LEFT(B41,7)))
A42: Ekow Nyamekye Tawiah | B42: 46204 | C42: / | D42: Ekow Nyamekye Tawiah | E42: Ekow Nyamekye Tawiah | F42: 46210.643 | H42: PCGH778 - General Support | I42: 4 | J42: PCGH778 - Support to Other Workstreams (3) (Proforest Limited(PCUK GBP)) | K42: (WS3: Deforestation) Deforestation Remote Risk Assessment | L42: TRUE | M42: Billed at a Fixed price | N42: =IF(B42="","",IF(ISNUMBER(B42),TEXT(B42,"YYYY-MM"),LEFT(B42,7)))
A43: Abel Ansu | B43: 46204 | C43: Supply of seedlings to Bitre/ Biaso Kasapin | D43: Abel Ansu | E43: Abel Ansu | F43: 46210.37 | H43: P13PC00A00 - Private Sector Companies | I43: 8 | K43: Personnel Cost | L43: FALSE | M43: Non-Billable | N43: =IF(B43="","",IF(ISNUMBER(B43),TEXT(B43,"YYYY-MM"),LEFT(B43,7)))
A44: Stephen Doso | B44: 46204 | C44: / | D44: Stephen Doso | E44: Stephen Doso | F44: 46209.537 | H44: PCGH738 | I44: 1.5 | J44: PCGH738 - Analysis and Reporting (3) (Barnsley International Limited) | K44: Analysis and Reporting (3) | L44: TRUE | M44: Billed at a Fixed price | N44: =IF(B44="","",IF(ISNUMBER(B44),TEXT(B44,"YYYY-MM"),LEFT(B44,7)))
A45: Stephen Doso | B45: 46204 | C45: / | D45: Stephen Doso | E45: Stephen Doso | F45: 46209.536 | H45: PCGH788 - CDC Boa & Mondoni CV-HCS Scoping | I45: 1 | J45: PCGH788 - Participatory mapping (CAMEROON DEVELOPMENT CORPORATION (CDC)) | K45: BOA: MAPPING AND REPORTING (2) | L45: TRUE | M45: Billed Manually | N45: =IF(B45="","",IF(ISNUMBER(B45),TEXT(B45,"YYYY-MM"),LEFT(B45,7)))
A46: Louis Defo | B46: 46204 | C46: participate to Cameroon cocoa week in order to do some stakeholdesr engagements | D46: Louis Defo | E46: Louis Defo | F46: 46209.313 | H46: PCGH787 | I46: 8 | J46: PCGH787 - Desk Study (3) (Proforest Limited(PCUK GBP)) | L46: TRUE | M46: Billed at a Fixed price | N46: =IF(B46="","",IF(ISNUMBER(B46),TEXT(B46,"YYYY-MM"),LEFT(B46,7)))
A47: Afua Serwah Akoto Prempeh | B47: 46204 | C47: / | D47: Afua Serwah Akoto Prempeh | E47: Afua Serwah Akoto Prempeh | F47: 46205.5 | H47: P23AC00C00 - FGMC | I47: 1 | L47: FALSE | M47: Non-Billable | N47: =IF(B47="","",IF(ISNUMBER(B47),TEXT(B47,"YYYY-MM"),LEFT(B47,7)))
A48: Abel Ansu | B48: 46203 | C48: Supply of seedlings to MTS sites (Bia Tano Forest reserve - Koforidua/ Assamang) | D48: Abel Ansu | E48: Abel Ansu | F48: 46210.369 | H48: P13PC00A00 - Private Sector Companies | I48: 8 | K48: Personnel Cost | L48: FALSE | M48: Non-Billable | N48: =IF(B48="","",IF(ISNUMBER(B48),TEXT(B48,"YYYY-MM"),LEFT(B48,7)))
A49: Stephen Doso | B49: 46203 | C49: / | D49: Stephen Doso | E49: Stephen Doso | F49: 46209.535 | H49: Non-Billable Tasks | I49: 1 | K49: Communication/Data/Training | L49: FALSE | M49: Non-Billable | N49: =IF(B49="","",IF(ISNUMBER(B49),TEXT(B49,"YYYY-MM"),LEFT(B49,7)))
A50: Stephen Doso | B50: 46203 | C50: / | D50: Stephen Doso | E50: Stephen Doso | F50: 46209.535 | H50: PCGH791 | I50: 3 | J50: PCGH791 - Stakeholder Consultations (3) (Rainforest Alliance Inc) | K50: Incorporating AFi in Proforest projects | L50: TRUE | M50: Billed at a Fixed price | N50: =IF(B50="","",IF(ISNUMBER(B50),TEXT(B50,"YYYY-MM"),LEFT(B50,7)))
A51: Stephen Doso | B51: 46203 | C51: / | D51: Stephen Doso | E51: Stephen Doso | F51: 46209.534 | H51: PCGH788 - CDC Boa & Mondoni CV-HCS Scoping | I51: 4 | J51: PCGH788 - Participatory mapping (CAMEROON DEVELOPMENT CORPORATION (CDC)) | K51: BOA: MAPPING AND REPORTING (2) | L51: TRUE | M51: Billed Manually | N51: =IF(B51="","",IF(ISNUMBER(B51),TEXT(B51,"YYYY-MM"),LEFT(B51,7)))
A52: Louis Defo | B52: 46203 | C52: revise the inception report done by the consultant and discuss with him | D52: Louis Defo | E52: Louis Defo | F52: 46209.312 | H52: P23AC00C00 - FGMC | I52: 8 | L52: FALSE | M52: Non-Billable | N52: =IF(B52="","",IF(ISNUMBER(B52),TEXT(B52,"YYYY-MM"),LEFT(B52,7)))
A53: Afua Serwah Akoto Prempeh | B53: 46203 | C53: / | D53: Afua Serwah Akoto Prempeh | E53: Afua Serwah Akoto Prempeh | F53: 46204.56 | H53: Non-Billable Tasks | I53: 8 | K53: Professional development and Knowledge sharing(training,global knowledge calls,exchange weeks) | L53: FALSE | M53: Non-Billable | N53: =IF(B53="","",IF(ISNUMBER(B53),TEXT(B53,"YYYY-MM"),LEFT(B53,7)))
A54: Ekow Nyamekye Tawiah | B54: 46203 | C54: / | D54: Ekow Nyamekye Tawiah | E54: Ekow Nyamekye Tawiah | F54: 46204.205 | H54: PCGH778 - General Support | I54: 4 | J54: PCGH778 - Support to Other Workstreams (3) (Proforest Limited(PCUK GBP)) | L54: TRUE | M54: Billed at a Fixed price | N54: =IF(B54="","",IF(ISNUMBER(B54),TEXT(B54,"YYYY-MM"),LEFT(B54,7)))
A55: Augustus Asamoah | B55: 46202 | C55: / | D55: Augustus Asamoah | E55: Augustus Asamoah | F55: 46210.479 | G55: Final Reporting | H55: PCGH784 | I55: 2 | J55: PCGH784 - Reporting (3) (Okeosisi Jonathan) | K55: Reporting | L55: TRUE | M55: Billed at a Fixed price | N55: =IF(B55="","",IF(ISNUMBER(B55),TEXT(B55,"YYYY-MM"),LEFT(B55,7)))
A56: Augustus Asamoah | B56: 46202 | C56: / | D56: Augustus Asamoah | E56: Augustus Asamoah | F56: 46210.478 | H56: P13QC00A00 - EFI Programme | I56: 1 | L56: FALSE | M56: Non-Billable | N56: =IF(B56="","",IF(ISNUMBER(B56),TEXT(B56,"YYYY-MM"),LEFT(B56,7)))
A57: Augustus Asamoah | B57: 46202 | C57: / | D57: Augustus Asamoah | E57: Augustus Asamoah | F57: 46210.478 | H57: P13NC00A00 - WALMART II | I57: 2 | K57: Follow up of seedling procurement, AFS, & Procurements | L57: FALSE | M57: Non-Billable | N57: =IF(B57="","",IF(ISNUMBER(B57),TEXT(B57,"YYYY-MM"),LEFT(B57,7)))
A58: Augustus Asamoah | B58: 46202 | C58: Call with Tim Ryden on J REDD | D58: Augustus Asamoah | E58: Augustus Asamoah | F58: 46210.478 | H58: P13PC00A00 - Private Sector Companies | I58: 1 | K58: coordination of MTS and related Activities | L58: FALSE | M58: Non-Billable | N58: =IF(B58="","",IF(ISNUMBER(B58),TEXT(B58,"YYYY-MM"),LEFT(B58,7)))
A59: Augustus Asamoah | B59: 46202 | C59: / | D59: Augustus Asamoah | E59: Augustus Asamoah | F59: 46210.476 | G59: Final Reporting | H59: PCGH784 | I59: 2 | J59: PCGH784 - Reporting (3) (Okeosisi Jonathan) | K59: Reporting | L59: TRUE | M59: Billed at a Fixed price | N59: =IF(B59="","",IF(ISNUMBER(B59),TEXT(B59,"YYYY-MM"),LEFT(B59,7)))
A60: Abel Ansu | B60: 46202 | C60: Supply of seedlings to MTS site | D60: Abel Ansu | E60: Abel Ansu | F60: 46210.368 | H60: P13PC00A00 - Private Sector Companies | I60: 8 | K60: Personnel Cost | L60: FALSE | M60: Non-Billable | N60: =IF(B60="","",IF(ISNUMBER(B60),TEXT(B60,"YYYY-MM"),LEFT(B60,7)))
A61: Stephen Doso | B61: 46202 | C61: / | D61: Stephen Doso | E61: Stephen Doso | F61: 46209.535 | H61: PCGH791 | I61: 5 | J61: PCGH791 - Stakeholder Consultations (3) (Rainforest Alliance Inc) | K61: Incorporating AFi in Proforest projects | L61: TRUE | M61: Billed at a Fixed price | N61: =IF(B61="","",IF(ISNUMBER(B61),TEXT(B61,"YYYY-MM"),LEFT(B61,7)))
A62: Stephen Doso | B62: 46202 | C62: / | D62: Stephen Doso | E62: Stephen Doso | F62: 46209.533 | H62: Non-Billable Tasks | I62: 1 | K62: Professional development and Knowledge sharing(training,global knowledge calls,exchange weeks) | L62: FALSE | M62: Non-Billable | N62: =IF(B62="","",IF(ISNUMBER(B62),TEXT(B62,"YYYY-MM"),LEFT(B62,7)))
A63: Louis Defo | B63: 46202 | C63: work on ToR of the workshop | D63: Louis Defo | E63: Louis Defo | F63: 46209.311 | H63: P23AC00C00 - FGMC | I63: 8 | L63: FALSE | M63: Non-Billable | N63: =IF(B63="","",IF(ISNUMBER(B63),TEXT(B63,"YYYY-MM"),LEFT(B63,7)))
A64: Afua Serwah Akoto Prempeh | B64: 46202 | C64: / | D64: Afua Serwah Akoto Prempeh | E64: Afua Serwah Akoto Prempeh | F64: 46204.56 | H64: Non-Billable Tasks | I64: 8 | K64: Professional development and Knowledge sharing(training,global knowledge calls,exchange weeks) | L64: FALSE | M64: Non-Billable | N64: =IF(B64="","",IF(ISNUMBER(B64),TEXT(B64,"YYYY-MM"),LEFT(B64,7)))
A65: Ekow Nyamekye Tawiah | B65: 46202 | C65: / | D65: Ekow Nyamekye Tawiah | E65: Ekow Nyamekye Tawiah | F65: 46203.192 | H65: PCGH778 - General Support | I65: 4 | J65: PCGH778 - Support to Other Workstreams (3) (Proforest Limited(PCUK GBP)) | L65: TRUE | M65: Billed at a Fixed price | N65: =IF(B65="","",IF(ISNUMBER(B65),TEXT(B65,"YYYY-MM"),LEFT(B65,7)))
A66: Augustus Asamoah | B66: 46199 | C66: / | D66: Augustus Asamoah | E66: Augustus Asamoah | F66: 46210.417 | H66: P13NC00A00 - WALMART II | I66: 1 | K66: Follow up of seedling procurement, AFS, & Procurements | L66: FALSE | M66: Non-Billable | N66: =IF(B66="","",IF(ISNUMBER(B66),TEXT(B66,"YYYY-MM"),LEFT(B66,7)))
A67: Augustus Asamoah | B67: 46199 | C67: / | D67: Augustus Asamoah | E67: Augustus Asamoah | F67: 46210.417 | H67: P13PC00A00 - Private Sector Companies | I67: 1 | K67: coordination of MTS and related Activities | L67: FALSE | M67: Non-Billable | N67: =IF(B67="","",IF(ISNUMBER(B67),TEXT(B67,"YYYY-MM"),LEFT(B67,7)))
A68: Augustus Asamoah | B68: 46199 | C68: / | D68: Augustus Asamoah | E68: Augustus Asamoah | F68: 46210.417 | H68: P13QC00A00 - EFI Programme | I68: 1 | K68: M&E Review | L68: FALSE | M68: Non-Billable | N68: =IF(B68="","",IF(ISNUMBER(B68),TEXT(B68,"YYYY-MM"),LEFT(B68,7)))
A69: Augustus Asamoah | B69: 46199 | C69: / | D69: Augustus Asamoah | E69: Augustus Asamoah | F69: 46210.417 | G69: Final Reporting | H69: PCGH784 | I69: 5 | J69: PCGH784 - Reporting (3) (Okeosisi Jonathan) | K69: Reporting | L69: TRUE | M69: Billed at a Fixed price | N69: =IF(B69="","",IF(ISNUMBER(B69),TEXT(B69,"YYYY-MM"),LEFT(B69,7)))
A70: Afua Serwah Akoto Prempeh | B70: 46199 | C70: / | D70: Afua Serwah Akoto Prempeh | E70: Afua Serwah Akoto Prempeh | F70: 46204.56 | H70: Non-Billable Tasks | I70: 8 | K70: Professional development and Knowledge sharing(training,global knowledge calls,exchange weeks) | L70: FALSE | M70: Non-Billable | N70: =IF(B70="","",IF(ISNUMBER(B70),TEXT(B70,"YYYY-MM"),LEFT(B70,7)))
A71: Abel Ansu | B71: 46199 | C71: Monitoring of lining and pegging at Biaso Kasapin (Bia Tano reserve) and seddlings transportation at Aboagyaa (Bia Tano reserve) | D71: Abel Ansu | E71: Abel Ansu | F71: 46203.636 | H71: P13PC00A00 - Private Sector Companies | I71: 8 | K71: Personnel Cost | L71: FALSE | M71: Non-Billable | N71: =IF(B71="","",IF(ISNUMBER(B71),TEXT(B71,"YYYY-MM"),LEFT(B71,7)))
A72: Ekow Nyamekye Tawiah | B72: 46199 | C72: / | D72: Ekow Nyamekye Tawiah | E72: Ekow Nyamekye Tawiah | F72: 46203.192 | H72: PCGH778 - General Support | I72: 4 | J72: PCGH778 - Support to Other Workstreams (3) (Proforest Limited(PCUK GBP)) | L72: TRUE | M72: Billed at a Fixed price | N72: =IF(B72="","",IF(ISNUMBER(B72),TEXT(B72,"YYYY-MM"),LEFT(B72,7)))
A73: Louis Defo | B73: 46199 | C73: annual leave | D73: Louis Defo | E73: Louis Defo | F73: 46202.328 | H73: P23AC00C00 - FGMC | I73: 8 | L73: FALSE | M73: Non-Billable | N73: =IF(B73="","",IF(ISNUMBER(B73),TEXT(B73,"YYYY-MM"),LEFT(B73,7)))
A74: Augustus Asamoah | B74: 46198 | C74: / | D74: Augustus Asamoah | E74: Augustus Asamoah | F74: 46210.416 | H74: P13PC00A00 - Private Sector Companies | I74: 2 | K74: coordination of MTS and related Activities | L74: FALSE | M74: Non-Billable | N74: =IF(B74="","",IF(ISNUMBER(B74),TEXT(B74,"YYYY-MM"),LEFT(B74,7)))
A75: Augustus Asamoah | B75: 46198 | C75: / | D75: Augustus Asamoah | E75: Augustus Asamoah | F75: 46210.416 | H75: P13NC00A00 - WALMART II | I75: 1 | K75: Follow up of seedling procurement, AFS, & Procurements | L75: FALSE | M75: Non-Billable | N75: =IF(B75="","",IF(ISNUMBER(B75),TEXT(B75,"YYYY-MM"),LEFT(B75,7)))
A76: Augustus Asamoah | B76: 46198 | C76: / | D76: Augustus Asamoah | E76: Augustus Asamoah | F76: 46210.416 | H76: P13QC00A00 - EFI Programme | I76: 1 | K76: Procurements - ToR | L76: FALSE | M76: Non-Billable | N76: =IF(B76="","",IF(ISNUMBER(B76),TEXT(B76,"YYYY-MM"),LEFT(B76,7)))
A77: Augustus Asamoah | B77: 46198 | C77: / | D77: Augustus Asamoah | E77: Augustus Asamoah | F77: 46210.416 | G77: Final Reporting | H77: PCGH784 | I77: 4 | J77: PCGH784 - Reporting (3) (Okeosisi Jonathan) | K77: Reporting | L77: TRUE | M77: Billed at a Fixed price | N77: =IF(B77="","",IF(ISNUMBER(B77),TEXT(B77,"YYYY-MM"),LEFT(B77,7)))
A78: Afua Serwah Akoto Prempeh | B78: 46198 | C78: / | D78: Afua Serwah Akoto Prempeh | E78: Afua Serwah Akoto Prempeh | F78: 46204.557 | H78: Non-Billable Tasks | I78: 8 | K78: Professional development and Knowledge sharing(training,global knowledge calls,exchange weeks) | L78: FALSE | M78: Non-Billable | N78: =IF(B78="","",IF(ISNUMBER(B78),TEXT(B78,"YYYY-MM"),LEFT(B78,7)))
A79: Abel Ansu | B79: 46198 | C79: To monitor and confirm seedlings supplied at Goamu camp (Bia Tano reserve) | D79: Abel Ansu | E79: Abel Ansu | F79: 46203.634 | H79: P13PC00A00 - Private Sector Companies | I79: 8 | K79: Personnel Cost | L79: FALSE | M79: Non-Billable | N79: =IF(B79="","",IF(ISNUMBER(B79),TEXT(B79,"YYYY-MM"),LEFT(B79,7)))
A80: Ekow Nyamekye Tawiah | B80: 46198 | C80: / | D80: Ekow Nyamekye Tawiah | E80: Ekow Nyamekye Tawiah | F80: 46203.192 | H80: PCGH778 - General Support | I80: 4 | J80: PCGH778 - Support to Other Workstreams (3) (Proforest Limited(PCUK GBP)) | L80: TRUE | M80: Billed at a Fixed price | N80: =IF(B80="","",IF(ISNUMBER(B80),TEXT(B80,"YYYY-MM"),LEFT(B80,7)))
A81: Louis Defo | B81: 46198 | C81: / | D81: Louis Defo | E81: Louis Defo | F81: 46202.326 | H81: PCGH787 | I81: 8 | J81: PCGH787 - Desk Study (3) (Proforest Limited(PCUK GBP)) | L81: TRUE | M81: Billed at a Fixed price | N81: =IF(B81="","",IF(ISNUMBER(B81),TEXT(B81,"YYYY-MM"),LEFT(B81,7)))
A82: Clement Obeng-Manu | B82: 46198 | C82: / | D82: Clement Obeng-Manu | E82: Clement Obeng-Manu | F82: 46195.718 | H82: PCGH776 - Deforestation Risk-Assessment Cashew-Coast | I82: 8 | J82: PCGH776 - Groundthruthing and Verification (3) (Cashew Coast Products Inc) | K82: Land cover classification, ground truthing and accuracy assessment | L82: TRUE | M82: Billed at a Fixed price | N82: =IF(B82="","",IF(ISNUMBER(B82),TEXT(B82,"YYYY-MM"),LEFT(B82,7)))
A83: Augustus Asamoah | B83: 46197 | C83: / | D83: Augustus Asamoah | E83: Augustus Asamoah | F83: 46210.416 | G83: Final Reporting | H83: PCGH784 | I83: 3 | J83: PCGH784 - Reporting (3) (Okeosisi Jonathan) | K83: Reporting | L83: TRUE | M83: Billed at a Fixed price | N83: =IF(B83="","",IF(ISNUMBER(B83),TEXT(B83,"YYYY-MM"),LEFT(B83,7)))
A84: Augustus Asamoah | B84: 46197 | C84: / | D84: Augustus Asamoah | E84: Augustus Asamoah | F84: 46210.394 | H84: P13PC00A00 - Private Sector Companies | I84: 3 | K84: coordination of MTS and related Activities | L84: FALSE | M84: Non-Billable | N84: =IF(B84="","",IF(ISNUMBER(B84),TEXT(B84,"YYYY-MM"),LEFT(B84,7)))
A85: Augustus Asamoah | B85: 46197 | C85: / | D85: Augustus Asamoah | E85: Augustus Asamoah | F85: 46210.394 | H85: P13QC00A00 - EFI Programme | I85: 2 | K85: M&E Review | L85: FALSE | M85: Non-Billable | N85: =IF(B85="","",IF(ISNUMBER(B85),TEXT(B85,"YYYY-MM"),LEFT(B85,7)))
A86: Abel Ansu | B86: 46197 | C86: Monitored seedlings transportation at Aboagyaa and Tokrom | D86: Abel Ansu | E86: Abel Ansu | F86: 46203.633 | H86: P13PC00A00 - Private Sector Companies | I86: 8 | K86: Personnel Cost | L86: FALSE | M86: Non-Billable | N86: =IF(B86="","",IF(ISNUMBER(B86),TEXT(B86,"YYYY-MM"),LEFT(B86,7)))
A87: Ekow Nyamekye Tawiah | B87: 46197 | C87: / | D87: Ekow Nyamekye Tawiah | E87: Ekow Nyamekye Tawiah | F87: 46203.192 | H87: PCGH778 - General Support | I87: 4 | J87: PCGH778 - Support to Other Workstreams (3) (Proforest Limited(PCUK GBP)) | L87: TRUE | M87: Billed at a Fixed price | N87: =IF(B87="","",IF(ISNUMBER(B87),TEXT(B87,"YYYY-MM"),LEFT(B87,7)))
A88: Louis Defo | B88: 46197 | C88: / | D88: Louis Defo | E88: Louis Defo | F88: 46202.325 | H88: PCGH787 | I88: 8 | J88: PCGH787 - Desk Study (3) (Proforest Limited(PCUK GBP)) | L88: TRUE | M88: Billed at a Fixed price | N88: =IF(B88="","",IF(ISNUMBER(B88),TEXT(B88,"YYYY-MM"),LEFT(B88,7)))
A89: Clement Obeng-Manu | B89: 46197 | C89: / | D89: Clement Obeng-Manu | E89: Clement Obeng-Manu | F89: 46205.566 | H89: PCGH776 - Deforestation Risk-Assessment Cashew-Coast | I89: 8 | J89: PCGH776 - Groundthruthing and Verification (3) (Cashew Coast Products Inc) | K89: Land cover classification, ground truthing and accuracy assessment | L89: TRUE | M89: Billed at a Fixed price | N89: =IF(B89="","",IF(ISNUMBER(B89),TEXT(B89,"YYYY-MM"),LEFT(B89,7)))
A90: Augustus Asamoah | B90: 46196 | C90: / | D90: Augustus Asamoah | E90: Augustus Asamoah | F90: 46210.417 | G90: Final Reporting | H90: PCGH784 | I90: 2 | J90: PCGH784 - Reporting (3) (Okeosisi Jonathan) | K90: Reporting | L90: TRUE | M90: Billed at a Fixed price | N90: =IF(B90="","",IF(ISNUMBER(B90),TEXT(B90,"YYYY-MM"),LEFT(B90,7)))
A91: Augustus Asamoah | B91: 46196 | C91: / | D91: Augustus Asamoah | E91: Augustus Asamoah | F91: 46210.393 | H91: P13PC00A00 - Private Sector Companies | I91: 2 | K91: coordination of MTS and related Activities | L91: FALSE | M91: Non-Billable | N91: =IF(B91="","",IF(ISNUMBER(B91),TEXT(B91,"YYYY-MM"),LEFT(B91,7)))
A92: Augustus Asamoah | B92: 46196 | C92: / | D92: Augustus Asamoah | E92: Augustus Asamoah | F92: 46210.393 | H92: P13NC00A00 - WALMART II | I92: 3 | K92: Follow up of seedling procurement, AFS, & Procurements | L92: FALSE | M92: Non-Billable | N92: =IF(B92="","",IF(ISNUMBER(B92),TEXT(B92,"YYYY-MM"),LEFT(B92,7)))
A93: Augustus Asamoah | B93: 46196 | C93: / | D93: Augustus Asamoah | E93: Augustus Asamoah | F93: 46210.417 | H93: P13QC00A00 - EFI Programme | I93: 1 | K93: Procurements - ToR | L93: FALSE | M93: Non-Billable | N93: =IF(B93="","",IF(ISNUMBER(B93),TEXT(B93,"YYYY-MM"),LEFT(B93,7)))
A94: Kwadwo Baniako Nti | B94: 46196 | C94: / | D94: Kwadwo Baniako Nti | E94: Kwadwo Baniako Nti | F94: 46205.513 | G94: Baseline Socio-Economic & Environmental Surveys | H94: PCGH762 - GVL HCSA Restoration Project | I94: 8 | J94: PCGH762 - Baseline Socio-Economic & Environmental Surveys (Golden Veroleum Liberia) | K94: Baseline Socio-Economic & Environmental Surveys | L94: TRUE | M94: Billed at a Fixed price | N94: =IF(B94="","",IF(ISNUMBER(B94),TEXT(B94,"YYYY-MM"),LEFT(B94,7)))
A95: Afua Serwah Akoto Prempeh | B95: 46196 | C95: / | D95: Afua Serwah Akoto Prempeh | E95: Afua Serwah Akoto Prempeh | F95: 46204.554 | G95: Output 4 | H95: P23AC00C00 - FGMC | I95: 8 | K95: P23AC03A00 - Project Management | L95: FALSE | M95: Non-Billable | N95: =IF(B95="","",IF(ISNUMBER(B95),TEXT(B95,"YYYY-MM"),LEFT(B95,7)))
A96: Abel Ansu | B96: 46196 | C96: Inspected roads that lead to Bitre MTS sites and ongoing lining and pegging at Bitre | D96: Abel Ansu | E96: Abel Ansu | F96: 46203.632 | H96: P13PC00A00 - Private Sector Companies | I96: 8 | K96: Personnel Cost | L96: FALSE | M96: Non-Billable | N96: =IF(B96="","",IF(ISNUMBER(B96),TEXT(B96,"YYYY-MM"),LEFT(B96,7)))
A97: Ekow Nyamekye Tawiah | B97: 46196 | C97: / | D97: Ekow Nyamekye Tawiah | E97: Ekow Nyamekye Tawiah | F97: 46203.192 | H97: PCGH778 - General Support | I97: 4 | J97: PCGH778 - Support to Other Workstreams (3) (Proforest Limited(PCUK GBP)) | L97: TRUE | M97: Billed at a Fixed price | N97: =IF(B97="","",IF(ISNUMBER(B97),TEXT(B97,"YYYY-MM"),LEFT(B97,7)))
A98: Louis Defo | B98: 46196 | C98: Read draft further mamping don,e by the consultant | D98: Louis Defo | E98: Louis Defo | F98: 46202.324 | H98: P23AC00C00 - FGMC | I98: 8 | L98: FALSE | M98: Non-Billable | N98: =IF(B98="","",IF(ISNUMBER(B98),TEXT(B98,"YYYY-MM"),LEFT(B98,7)))
A99: Clement Obeng-Manu | B99: 46196 | C99: / | D99: Clement Obeng-Manu | E99: Clement Obeng-Manu | F99: 46195.717 | H99: PCGH776 - Deforestation Risk-Assessment Cashew-Coast | I99: 8 | J99: PCGH776 - Groundthruthing and Verification (3) (Cashew Coast Products Inc) | K99: Land cover classification, ground truthing and accuracy assessment | L99: TRUE | M99: Billed at a Fixed price | N99: =IF(B99="","",IF(ISNUMBER(B99),TEXT(B99,"YYYY-MM"),LEFT(B99,7)))
A100: Augustus Asamoah | B100: 46195 | C100: Report - Environment Section | D100: Augustus Asamoah | E100: Augustus Asamoah | F100: 46210.416 | G100: Final Reporting | H100: PCGH784 | I100: 0 | J100: PCGH784 - Reporting (3) (Okeosisi Jonathan) | K100: Reporting | L100: TRUE | M100: Billed at a Fixed price | N100: =IF(B100="","",IF(ISNUMBER(B100),TEXT(B100,"YYYY-MM"),LEFT(B100,7)))
A101: Augustus Asamoah | B101: 46195 | C101: Fauna report | D101: Augustus Asamoah | E101: Augustus Asamoah | F101: 46210.415 | H101: PCGH771 | I101: 0 | J101: PCGH771 - Analysis and Reporting (3) (Okeosisi Jonathan) | K101: Analysis and Reporting (Reporting) | L101: TRUE | M101: Billed at a Fixed price | N101: =IF(B101="","",IF(ISNUMBER(B101),TEXT(B101,"YYYY-MM"),LEFT(B101,7)))
A102: Augustus Asamoah | B102: 46195 | C102: / | D102: Augustus Asamoah | E102: Augustus Asamoah | F102: 46210.394 | H102: P13QC00A00 - EFI Programme | I102: 0 | K102: M&E Review | L102: FALSE | M102: Non-Billable | N102: =IF(B102="","",IF(ISNUMBER(B102),TEXT(B102,"YYYY-MM"),LEFT(B102,7)))
A103: Augustus Asamoah | B103: 46195 | C103: / | D103: Augustus Asamoah | E103: Augustus Asamoah | F103: 46210.389 | H103: P13PC00A00 - Private Sector Companies | I103: 2 | K103: coordination of MTS and related Activities | L103: FALSE | M103: Non-Billable | N103: =IF(B103="","",IF(ISNUMBER(B103),TEXT(B103,"YYYY-MM"),LEFT(B103,7)))
A104: Augustus Asamoah | B104: 46195 | C104: / | D104: Augustus Asamoah | E104: Augustus Asamoah | F104: 46210.384 | H104: P13QC00A00 - EFI Programme | I104: 3 | K104: Procurements - ToR | L104: FALSE | M104: Non-Billable | N104: =IF(B104="","",IF(ISNUMBER(B104),TEXT(B104,"YYYY-MM"),LEFT(B104,7)))
A105: Augustus Asamoah | B105: 46195 | C105: / | D105: Augustus Asamoah | E105: Augustus Asamoah | F105: 46210.384 | H105: P13NC00A00 - WALMART II | I105: 3 | K105: Follow up of seedling procurement, AFS, & Procurements | L105: FALSE | M105: Non-Billable | N105: =IF(B105="","",IF(ISNUMBER(B105),TEXT(B105,"YYYY-MM"),LEFT(B105,7)))
...

Sheet ALLOCATIONS
A1: Employee (Odoo name) | B1: Project (Odoo name) | C1: Month (YYYY-MM) | D1: Allocated Hours
A2: Afua Serwah Akoto Prempeh | B2: Non-Billable Tasks | C2: 2026-01
A3: Afua Serwah Akoto Prempeh | B3: P23AC00C00 - FGMC | C3: 2026-01
A4: Augustus Asamoah | B4: Non-Billable Tasks | C4: 2026-01
A5: Augustus Asamoah | B5: P13NC00A00 - WALMART II | C5: 2026-01
A6: Augustus Asamoah | B6: P13QC00A00 - EFI Programme | C6: 2026-01
A7: Augustus Asamoah | B7: PCGH769 | C7: 2026-01
A8: Augustus Asamoah | B8: PCGH771 | C8: 2026-01
A9: Clement Obeng-Manu | B9: Non-Billable Tasks | C9: 2026-01
A10: Clement Obeng-Manu | B10: PCGH722 | C10: 2026-01
A11: Clement Obeng-Manu | B11: PCGH752 | C11: 2026-01
A12: Clement Obeng-Manu | B12: PCGH769 | C12: 2026-01
A13: Daleba Bernard Kpenahi Raymond | B13: Non-Billable Tasks | C13: 2026-01
... A390: Stephen Doso | B390: PCGH788 - CDC Boa & Mondoni CV-HCS Scoping | C390: 2026-07

Sheet MAPPING
A1: EMPLOYEE MAPPING | E1: PROJECT MAPPING
A2: Odoo Employee Name | B2: Dashboard Staff ID | C2: Dashboard Staff Name | E2: Odoo Project Name | F2: Dashboard Project Name | G2: Program
A3: Abel Ansu | B3: STF-001 | C3: Abel Ansu | E3: Business and Project Management Training | F3: Business and Project Management Training
A4: Adwoa Fremah Ntosour-Amponsem | B4: STF-002 | C4: Adwoa Fremah Ntosour-Amponsem | E4: Global Internal Projects (GIPs) | F4: Global Internal Projects (GIPs)
A5: Afua Serwah Akoto Prempeh | B5: STF-003 | C5: Afua Serwah Akoto Prempeh | E5: Internal | F5: Internal
A6: Augustus Asamoah | B6: STF-004 | C6: Augustus Asamoah | E6: Non-Billable Tasks | F6: Non-Billable Tasks
A7: Clement Obeng-Manu | B7: STF-005 | C7: Clement Obeng-Manu | E7: P13GC00A00 - GAC Ulula | F7: GAC Ulula
A8: Daleba Bernard Kpenahi Raymond | B8: STF-006 | C8: Daleba Bernard Kpenahi Raymond | E8: P13LC00A00 - FAO Support in Cameroon | F8: FAO Support in Cameroon
A9: Ebenezer Gyadu | B9: STF-007 | C9: Ebenezer Gyadu | E9: P13NC00A00 - WALMART II | F9: WALMART II
A10: Ekow Nyamekye Tawiah | B10: STF-008 | C10: Ekow Nyamekye Tawiah | E10: P13PC00A00 - Private Sector Companies | F10: Private Sector Companies
A11: Ernestina Incoom | B11: STF-009 | C11: Ernestina Incoom | E11: P13QC00A00 - EFI Programme | F11: EFI Programme
A12: Frederick Antwi | B12: STF-010 | C12: Frederick Antwi | E12: P23AC00C00 - FGMC | F12: FGMC
A13: Helena Tetteh | B13: STF-011 | C13: Helena Tetteh | E13: PCGH686 | F13: PCGH686
A14: Jacqueline Nyakutse Afua | B14: STF-012 | C14: Jacqueline Nyakutse Afua | E14: PCGH722 | F14: PCGH722
... A25: Stephen Doso | B25: STF-023 | C25: Stephen Doso | E25: PCGH769 | F25: PCGH769
E26: PCGH771 | F26: PCGH771
E27: PCGH772 | F27: PCGH772
E28: PCGH774 -Evaluation Deep-Dive Action Plans by Socfin Group | F28: Evaluation Deep-Dive Action Plans by Socfin Group
E29: PCGH775 - ESDD of Valency Operations for FMO | F29: ESDD of Valency Operations for FMO
E30: PCGH776 - Deforestation Risk-Assessment Cashew-Coast | F30: Deforestation Risk-Assessment Cashew-Coast
E31: PCGH777 | F31: PCGH777
E32: PCGH778 - General Support | F32: General Support
E33: PCGH779 - Cote d'Ivoire） | F33: Cote d'Ivoire）
E34: PCGH780 - Nigeria | F34: Nigeria
E35: PCGH783 - Zimbabwe HRDD | F35: Zimbabwe HRDD
E36: PCGH784 | F36: PCGH784
E37: PCGH785 | F37: PCGH785
... E45: PCGH793 | F45: PCGH793

Sheet UPLOAD
A1: CHECKS (all must be OK before uploading)
A2: Total hours reconcile (RAW_004 = UPLOAD): | C2: =IF(ROUND(SUM(RAW_004!I2:I10001)-SUM(G8:G1007),2)=0,"OK","MISMATCH: "&TEXT(SUM(RAW_004!I2:I10001)-SUM(G8:G1007),"0.00")&" hrs not in UPLOAD - add missing rows in ALLOCATIONS")
A3: All employees mapped: | C3: =IF(SUMPRODUCT((RAW_004!D2:D10001<>"")*ISNA(MATCH(RAW_004!D2:D10001,MAPPING!A3:A302,0)))=0,"OK","UNMAPPED EMPLOYEES: add them in MAPPING")
A4: All projects mapped: | C4: =IF(SUMPRODUCT((RAW_004!H2:H10001<>"")*ISNA(MATCH(RAW_004!H2:H10001,MAPPING!E3:E302,0)))=0,"OK","UNMAPPED PROJECTS: add them in MAPPING")
A6: UPLOAD DATA - while on this tab, File > Save As > CSV, then upload the CSV to the TFS Dashboard
A7: Staff ID | B7: Staff Name | C7: Project | D7: Program | E7: Period | F7: Allocated Hours | G7: Actual Hours | H7: Variance (Actual - Allocated)
A8: =IF(ALLOCATIONS!A2="","",IFERROR(VLOOKUP(ALLOCATIONS!A2,MAPPING!$A$3:$C$302,2,FALSE),"UNMAPPED")) | B8: =IF(ALLOCATIONS!A2="","",IFERROR(VLOOKUP(ALLOCATIONS!A2,MAPPING!$A$3:$C$302,3,FALSE),ALLOCATIONS!A2)) | C8: =IF(ALLOCATIONS!A2="","",IFERROR(VLOOKUP(ALLOCATIONS!B2,MAPPING!$E$3:$G$302,2,FALSE),"UNMAPPED")) | D8: =IF(ALLOCATIONS!A2="","",IFERROR(IF(VLOOKUP(ALLOCATIONS!B2,MAPPING!$E$3:$G$302,3,FALSE)="","",VLOOKUP(ALLOCATIONS!B2,MAPPING!$E$3:$G$302,3,FALSE)),"")) | E8: =IF(ALLOCATIONS!A2="","",ALLOCATIONS!C2) | F8: =IF(ALLOCATIONS!A2="","",IF(ALLOCATIONS!D2="",0,ALLOCATIONS!D2)) | G8: =IF(ALLOCATIONS!A2="","",SUMIFS(RAW_004!$I$2:$I$10001,RAW_004!$D$2:$D$10001,ALLOCATIONS!A2,RAW_004!$H$2:$H$10001,ALLOCATIONS!B2,RAW_004!$N$2:$N$10001,ALLOCATIONS!C2)) | H8: =IF(A8="","",G8-F8)
A9: =IF(ALLOCATIONS!A3="","",IFERROR(VLOOKUP(ALLOCATIONS!A3,MAPPING!$A$3:$C$302,2,FALSE),"UNMAPPED")) | B9: =IF(ALLOCATIONS!A3="","",IFERROR(VLOOKUP(ALLOCATIONS!A3,MAPPING!$A$3:$C$302,3,FALSE),ALLOCATIONS!A3)) | C9: =IF(ALLOCATIONS!A3="","",IFERROR(VLOOKUP(ALLOCATIONS!B3,MAPPING!$E$3:$G$302,2,FALSE),"UNMAPPED")) | D9: =IF(ALLOCATIONS!A3="","",IFERROR(IF(VLOOKUP(ALLOCATIONS!B3,MAPPING!$E$3:$G$302,3,FALSE)="","",VLOOKUP(ALLOCATIONS!B3,MAPPING!$E$3:$G$302,3,FALSE)),"")) | E9: =IF(ALLOCATIONS!A3="","",ALLOCATIONS!C3) | F9: =IF(ALLOCATIONS!A3="","",IF(ALLOCATIONS!D3="",0,ALLOCATIONS!D3)) | G9: =IF(ALLOCATIONS!A3="","",SUMIFS(RAW_004!$I$2:$I$10001,RAW_004!$D$2:$D$10001,ALLOCATIONS!A3,RAW_004!$H$2:$H$10001,ALLOCATIONS!B3,RAW_004!$N$2:$N$10001,ALLOCATIONS!C3)) | H9: =IF(A9="","",G9-F9)
A10: =IF(ALLOCATIONS!A4="","",IFERROR(VLOOKUP(ALLOCATIONS!A4,MAPPING!$A$3:$C$302,2,FALSE),"UNMAPPED")) | B10: =IF(ALLOCATIONS!A4="","",IFERROR(VLOOKUP(ALLOCATIONS!A4,MAPPING!$A$3:$C$302,3,FALSE),ALLOCATIONS!A4)) | C10: =IF(ALLOCATIONS!A4="","",IFERROR(VLOOKUP(ALLOCATIONS!B4,MAPPING!$E$3:$G$302,2,FALSE),"UNMAPPED")) | D10: =IF(ALLOCATIONS!A4="","",IFERROR(IF(VLOOKUP(ALLOCATIONS!B4,MAPPING!$E$3:$G$302,3,FALSE)="","",VLOOKUP(ALLOCATIONS!B4,MAPPING!$E$3:$G$302,3,FALSE)),"")) | E10: =IF(ALLOCATIONS!A4="","",ALLOCATIONS!C4) | F10: =IF(ALLOCATIONS!A4="","",IF(ALLOCATIONS!D4="",0,ALLOCATIONS!D4)) | G10: =IF(ALLOCATIONS!A4="","",SUMIFS(RAW_004!$I$2:$I$10001,RAW_004!$D$2:$D$10001,ALLOCATIONS!A4,RAW_004!$H$2:$H$10001,ALLOCATIONS!B4,RAW_004!$N$2:$N$10001,ALLOCATIONS!C4)) | H10: =IF(A10="","",G10-F10)
A11: =IF(ALLOCATIONS!A5="","",IFERROR(VLOOKUP(ALLOCATIONS!A5,MAPPING!$A$3:$C$302,2,FALSE),"UNMAPPED")) | B11: =IF(ALLOCATIONS!A5="","",IFERROR(VLOOKUP(ALLOCATIONS!A5,MAPPING!$A$3:$C$302,3,FALSE),ALLOCATIONS!A5)) | C11: =IF(ALLOCATIONS!A5="","",IFERROR(VLOOKUP(ALLOCATIONS!B5,MAPPING!$E$3:$G$302,2,FALSE),"UNMAPPED")) | D11: =IF(ALLOCATIONS!A5="","",IFERROR(IF(VLOOKUP(ALLOCATIONS!B5,MAPPING!$E$3:$G$302,3,FALSE)="","",VLOOKUP(ALLOCATIONS!B5,MAPPING!$E$3:$G$302,3,FALSE)),"")) | E11: =IF(ALLOCATIONS!A5="","",ALLOCATIONS!C5) | F11: =IF(ALLOCATIONS!A5="","",IF(ALLOCATIONS!D5="",0,ALLOCATIONS!D5)) | G11: =IF(ALLOCATIONS!A5="","",SUMIFS(RAW_004!$I$2:$I$10001,RAW_004!$D$2:$D$10001,ALLOCATIONS!A5,RAW_004!$H$2:$H$10001,ALLOCATIONS!B5,RAW_004!$N$2:$N$10001,ALLOCATIONS!C5)) | H11: =IF(A11="","",G11-F11)
A12: =IF(ALLOCATIONS!A6="","",IFERROR(VLOOKUP(ALLOCATIONS!A6,MAPPING!$A$3:$C$302,2,FALSE),"UNMAPPED")) | B12: =IF(ALLOCATIONS!A6="","",IFERROR(VLOOKUP(ALLOCATIONS!A6,MAPPING!$A$3:$C$302,3,FALSE),ALLOCATIONS!A6)) | C12: =IF(ALLOCATIONS!A6="","",IFERROR(VLOOKUP(ALLOCATIONS!B6,MAPPING!$E$3:$G$302,2,FALSE),"UNMAPPED")) | D12: =IF(ALLOCATIONS!A6="","",IFERROR(IF(VLOOKUP(ALLOCATIONS!B6,MAPPING!$E$3:$G$302,3,FALSE)="","",VLOOKUP(ALLOCATIONS!B6,MAPPING!$E$3:$G$302,3,FALSE)),"")) | E12: =IF(ALLOCATIONS!A6="","",ALLOCATIONS!C6) | F12: =IF(ALLOCATIONS!A6="","",IF(ALLOCATIONS!D6="",0,ALLOCATIONS!D6)) | G12: =IF(ALLOCATIONS!A6="","",SUMIFS(RAW_004!$I$2:$I$10001,RAW_004!$D$2:$D$10001,ALLOCATIONS!A6,RAW_004!$H$2:$H$10001,ALLOCATIONS!B6,RAW_004!$N$2:$N$10001,ALLOCATIONS!C6)) | H12: =IF(A12="","",G12-F12)
A13: =IF(ALLOCATIONS!A7="","",IFERROR(VLOOKUP(ALLOCATIONS!A7,MAPPING!$A$3:$C$302,2,FALSE),"UNMAPPED")) | B13: =IF(ALLOCATIONS!A7="","",IFERROR(VLOOKUP(ALLOCATIONS!A7,MAPPING!$A$3:$C$302,3,FALSE),ALLOCATIONS!A7)) | C13: =IF(ALLOCATIONS!A7="","",IFERROR(VLOOKUP(ALLOCATIONS!B7,MAPPING!$E$3:$G$302,2,FALSE),"UNMAPPED")) | D13: =IF(ALLOCATIONS!A7="","",IFERROR(IF(VLOOKUP(ALLOCATIONS!B7,MAPPING!$E$3:$G$302,3,FALSE)="","",VLOOKUP(ALLOCATIONS!B7,MAPPING!$E$3:$G$302,3,FALSE)),"")) | E13: =IF(ALLOCATIONS!A7="","",ALLOCATIONS!C7) | F13: =IF(ALLOCATIONS!A7="","",IF(ALLOCATIONS!D7="",0,ALLOCATIONS!D7)) | G13: =IF(ALLOCATIONS!A7="","",SUMIFS(RAW_004!$I$2:$I$10001,RAW_004!$D$2:$D$10001,ALLOCATIONS!A7,RAW_004!$H$2:$H$10001,ALLOCATIONS!B7,RAW_004!$N$2:$N$10001,ALLOCATIONS!C7)) | H13: =IF(A13="","",G13-F13)
A14: =IF(ALLOCATIONS!A8="","",IFERROR(VLOOKUP(ALLOCATIONS!A8,MAPPING!$A$3:$C$302,2,FALSE),"UNMAPPED")) | B14: =IF(ALLOCATIONS!A8="","",IFERROR(VLOOKUP(ALLOCATIONS!A8,MAPPING!$A$3:$C$302,3,FALSE),ALLOCATIONS!A8)) | C14: =IF(ALLOCATIONS!A8="","",IFERROR(VLOOKUP(ALLOCATIONS!B8,MAPPING!$E$3:$G$302,2,FALSE),"UNMAPPED")) | D14: =IF(ALLOCATIONS!A8="","",IFERROR(IF(VLOOKUP(ALLOCATIONS!B8,MAPPING!$E$3:$G$302,3,FALSE)="","",VLOOKUP(ALLOCATIONS!B8,MAPPING!$E$3:$G$302,3,FALSE)),"")) | E14: =IF(ALLOCATIONS!A8="","",ALLOCATIONS!C8) | F14: =IF(ALLOCATIONS!A8="","",IF(ALLOCATIONS!D8="",0,ALLOCATIONS!D8)) | G14: =IF(ALLOCATIONS!A8="","",SUMIFS(RAW_004!$I$2:$I$10001,RAW_004!$D$2:$D$10001,ALLOCATIONS!A8,RAW_004!$H$2:$H$10001,ALLOCATIONS!B8,RAW_004!$N$2:$N$10001,ALLOCATIONS!C8)) | H14: =IF(A14="","",G14-F14)
A15: =IF(ALLOCATIONS!A9="","",IFERROR(VLOOKUP(ALLOCATIONS!A9,MAPPING!$A$3:$C$302,2,FALSE),"UNMAPPED")) | B15: =IF(ALLOCATIONS!A9="","",IFERROR(VLOOKUP(ALLOCATIONS!A9,MAPPING!$A$3:$C$302,3,FALSE),ALLOCATIONS!A9)) | C15: =IF(ALLOCATIONS!A9="","",IFERROR(VLOOKUP(ALLOCATIONS!B9,MAPPING!$E$3:$G$302,2,FALSE),"UNMAPPED")) | D15: =IF(ALLOCATIONS!A9="","",IFERROR(IF(VLOOKUP(ALLOCATIONS!B9,MAPPING!$E$3:$G$302,3,FALSE)="","",VLOOKUP(ALLOCATIONS!B9,MAPPING!$E$3:$G$302,3,FALSE)),"")) | E15: =IF(ALLOCATIONS!A9="","",ALLOCATIONS!C9) | F15: =IF(ALLOCATIONS!A9="","",IF(ALLOCATIONS!D9="",0,ALLOCATIONS!D9)) | G15: =IF(ALLOCATIONS!A9="","",SUMIFS(RAW_004!$I$2:$I$10001,RAW_004!$D$2:$D$10001,ALLOCATIONS!A9,RAW_004!$H$2:$H$10001,ALLOCATIONS!B9,RAW_004!$N$2:$N$10001,ALLOCATIONS!C9)) | H15: =IF(A15="","",G15-F15)
A16: =IF(ALLOCATIONS!A10="","",IFERROR(VLOOKUP(ALLOCATIONS!A10,MAPPING!$A$3:$C$302,2,FALSE),"UNMAPPED")) | B16: =IF(ALLOCATIONS!A10="","",IFERROR(VLOOKUP(ALLOCATIONS!A10,MAPPING!$A$3:$C$302,3,FALSE),ALLOCATIONS!A10)) | C16: =IF(ALLOCATIONS!A10="","",IFERROR(VLOOKUP(ALLOCATIONS!B10,MAPPING!$E$3:$G$302,2,FALSE),"UNMAPPED")) | D16: =IF(ALLOCATIONS!A10="","",IFERROR(IF(VLOOKUP(ALLOCATIONS!B10,MAPPING!$E$3:$G$302,3,FALSE)="","",VLOOKUP(ALLOCATIONS!B10,MAPPING!$E$3:$G$302,3,FALSE)),"")) | E16: =IF(ALLOCATIONS!A10="","",ALLOCATIONS!C10) | F16: =IF(ALLOCATIONS!A10="","",IF(ALLOCATIONS!D10="",0,ALLOCATIONS!D10)) | G16: =IF(ALLOCATIONS!A10="","",SUMIFS(RAW_004!$I$2:$I$10001,RAW_004!$D$2:$D$10001,ALLOCATIONS!A10,RAW_004!$H$2:$H$10001,ALLOCATIONS!B10,RAW_004!$N$2:$N$10001,ALLOCATIONS!C10)) | H16: =IF(A16="","",G16-F16)
A17: =IF(ALLOCATIONS!A11="","",IFERROR(VLOOKUP(ALLOCATIONS!A11,MAPPING!$A$3:$C$302,2,FALSE),"UNMAPPED")) | B17: =IF(ALLOCATIONS!A11="","",IFERROR(VLOOKUP(ALLOCATIONS!A11,MAPPING!$A$3:$C$302,3,FALSE),ALLOCATIONS!A11)) | C17: =IF(ALLOCATIONS!A11="","",IFERROR(VLOOKUP(ALLOCATIONS!B11,MAPPING!$E$3:$G$302,2,FALSE),"UNMAPPED")) | D17: =IF(ALLOCATIONS!A11="","",IFERROR(IF(VLOOKUP(ALLOCATIONS!B11,MAPPING!$E$3:$G$302,3,FALSE)="","",VLOOKUP(ALLOCATIONS!B11,MAPPING!$E$3:$G$302,3,FALSE)),"")) | E17: =IF(ALLOCATIONS!A11="","",ALLOCATIONS!C11) | F17: =IF(ALLOCATIONS!A11="","",IF(ALLOCATIONS!D11="",0,ALLOCATIONS!D11)) | G17: =IF(ALLOCATIONS!A11="","",SUMIFS(RAW_004!$I$2:$I$10001,RAW_004!$D$2:$D$10001,ALLOCATIONS!A11,RAW_004!$H$2:$H$10001,ALLOCATIONS!B11,RAW_004!$N$2:$N$10001,ALLOCATIONS!C11)) | H17: =IF(A17="","",G17-F17)
A18: =IF(ALLOCATIONS!A12="","",IFERROR(VLOOKUP(ALLOCATIONS!A12,MAPPING!$A$3:$C$302,2,FALSE),"UNMAPPED")) | B18: =IF(ALLOCATIONS!A12="","",IFERROR(VLOOKUP(ALLOCATIONS!A12,MAPPING!$A$3:$C$302,3,FALSE),ALLOCATIONS!A12)) | C18: =IF(ALLOCATIONS!A12="","",IFERROR(VLOOKUP(ALLOCATIONS!B12,MAPPING!$E$3:$G$302,2,FALSE),"UNMAPPED")) | D18: =IF(ALLOCATIONS!A12="","",IFERROR(IF(VLOOKUP(ALLOCATIONS!B12,MAPPING!$E$3:$G$302,3,FALSE)="","",VLOOKUP(ALLOCATIONS!B12,MAPPING!$E$3:$G$302,3,FALSE)),"")) | E18: =IF(ALLOCATIONS!A12="","",ALLOCATIONS!C12) | F18: =IF(ALLOCATIONS!A12="","",IF(ALLOCATIONS!D12="",0,ALLOCATIONS!D12)) | G18: =IF(ALLOCATIONS!A12="","",SUMIFS(RAW_004!$I$2:$I$10001,RAW_004!$D$2:$D$10001,ALLOCATIONS!A12,RAW_004!$H$2:$H$10001,ALLOCATIONS!B12,RAW_004!$N$2:$N$10001,ALLOCATIONS!C12)) | H18: =IF(A18="","",G18-F18)
A19: =IF(ALLOCATIONS!A13="","",IFERROR(VLOOKUP(ALLOCATIONS!A13,MAPPING!$A$3:$C$302,2,FALSE),"UNMAPPED")) | B19: =IF(ALLOCATIONS!A13="","",IFERROR(VLOOKUP(ALLOCATIONS!A13,MAPPING!$A$3:$C$302,3,FALSE),ALLOCATIONS!A13)) | C19: =IF(ALLOCATIONS!A13="","",IFERROR(VLOOKUP(ALLOCATIONS!B13,MAPPING!$E$3:$G$302,2,FALSE),"UNMAPPED")) | D19: =IF(ALLOCATIONS!A13="","",IFERROR(IF(VLOOKUP(ALLOCATIONS!B13,MAPPING!$E$3:$G$302,3,FALSE)="","",VLOOKUP(ALLOCATIONS!B13,MAPPING!$E$3:$G$302,3,FALSE)),"")) | E19: =IF(ALLOCATIONS!A13="","",ALLOCATIONS!C13) | F19: =IF(ALLOCATIONS!A13="","",IF(ALLOCATIONS!D13="",0,ALLOCATIONS!D13)) | G19: =IF(ALLOCATIONS!A13="","",SUMIFS(RAW_004!$I$2:$I$10001,RAW_004!$D$2:$D$10001,ALLOCATIONS!A13,RAW_004!$H$2:$H$10001,ALLOCATIONS!B13,RAW_004!$N$2:$N$10001,ALLOCATIONS!C13)) | H19: =IF(A19="","",G19-F19)
... A1007: =IF(ALLOCATIONS!A1001="","",IFERROR(VLOOKUP(ALLOCATIONS!A1001,MAPPING!$A$3:$C$302,2,FALSE),"UNMAPPED")) | B1007: =IF(ALLOCATIONS!A1001="","",IFERROR(VLOOKUP(ALLOCATIONS!A1001,MAPPING!$A$3:$C$302,3,FALSE),ALLOCATIONS!A1001)) | C1007: =IF(ALLOCATIONS!A1001="","",IFERROR(VLOOKUP(ALLOCATIONS!B1001,MAPPING!$E$3:$G$302,2,FALSE),"UNMAPPED")) | D1007: =IF(ALLOCATIONS!A1001="","",IFERROR(IF(VLOOKUP(ALLOCATIONS!B1001,MAPPING!$E$3:$G$302,3,FALSE)="","",VLOOKUP(ALLOCATIONS!B1001,MAPPING!$E$3:$G$302,3,FALSE)),"")) | E1007: =IF(ALLOCATIONS!A1001="","",ALLOCATIONS!C1001) | F1007: =IF(ALLOCATIONS!A1001="","",IF(ALLOCATIONS!D1001="",0,ALLOCATIONS!D1001)) | G1007: =IF(ALLOCATIONS!A1001="","",SUMIFS(RAW_004!$I$2:$I$10001,RAW_004!$D$2:$D$10001,ALLOCATIONS!A1001,RAW_004!$H$2:$H$10001,ALLOCATIONS!B1001,RAW_004!$N$2:$N$10001,ALLOCATIONS!C1001)) | H1007: =IF(A1007="","",G1007-F1007)
